stockstash/__init__.py
stockstash/cache.py
stockstash/providers.py
stockstash/ranges.py
stockstash/storage.py
stockstash-0.1.dist-info/METADATA
stockstash-0.1.dist-info/WHEEL
stockstash-0.1.dist-info/top_level.txt
stockstash-0.1.dist-info/RECORD
