Metadata-Version: 2.4
Name: stockstash
Version: 0.1
Summary: Intelligent time-series caching with Parquet and gap-aware incremental downloads
Author-email: AndreChang <andrechang67@gmail.com>
Project-URL: Homepage, https://github.com/Andrechang/stockstash
Project-URL: Repository, https://github.com/Andrechang/stockstash
Project-URL: Issues, https://github.com/Andrechang/stockstash/issues
Keywords: timeseries,cache,parquet,finance,yfinance,pandas
Classifier: Programming Language :: Python :: 3
Classifier: Operating System :: OS Independent
Classifier: Intended Audience :: Developers
Classifier: Topic :: Scientific/Engineering :: Information Analysis
Classifier: Topic :: Software Development :: Libraries
Requires-Python: >=3.9
Requires-Dist: pandas>=1.5
Requires-Dist: pyarrow>=10.0
Requires-Dist: yfinance>=0.2
